odoo10_addon_account_invoice_accrual_merge-10.0.1.0.0.99.dev10-nspkg.pth
odoo/addons/account_invoice_accrual_merge/README.rst
odoo/addons/account_invoice_accrual_merge/__init__.py
odoo/addons/account_invoice_accrual_merge/__manifest__.py
odoo/addons/account_invoice_accrual_merge/i18n/account_invoice_accrual_merge.pot
odoo/addons/account_invoice_accrual_merge/i18n/es.po
odoo/addons/account_invoice_accrual_merge/models/__init__.py
odoo/addons/account_invoice_accrual_merge/models/account_invoice.py
odoo/addons/account_invoice_accrual_merge/readme/CONTRIBUTORS.rst
odoo/addons/account_invoice_accrual_merge/readme/DESCRIPTION.rst
odoo/addons/account_invoice_accrual_merge/static/description/icon.png
odoo/addons/account_invoice_accrual_merge/static/description/index.html
odoo10_addon_account_invoice_accrual_merge-10.0.1.0.0.99.dev10.dist-info/METADATA
odoo10_addon_account_invoice_accrual_merge-10.0.1.0.0.99.dev10.dist-info/WHEEL
odoo10_addon_account_invoice_accrual_merge-10.0.1.0.0.99.dev10.dist-info/namespace_packages.txt
odoo10_addon_account_invoice_accrual_merge-10.0.1.0.0.99.dev10.dist-info/top_level.txt
odoo10_addon_account_invoice_accrual_merge-10.0.1.0.0.99.dev10.dist-info/RECORD
