Metadata-Version: 2.1
Name: odoo10-addon-account-invoice-accrual-merge
Version: 10.0.1.0.0.99.dev10
Summary: Account invoice accrual merge
Home-page: http://www.bcim.be
Author: BCIM sprl,Odoo Community Association (OCA)
Author-email: support@odoo-community.org
License: AGPL-3
Platform: UNKNOWN
Classifier: Programming Language :: Python
Classifier: Framework :: Odoo
Classifier: License :: OSI Approved :: GNU Affero General Public License v3
Requires-Python: ~=2.7
Requires-Dist: odoo10-addon-account-invoice-accrual
Requires-Dist: odoo10-addon-account-invoice-merge
Requires-Dist: odoo (<10.1dev,>=10.0)
